{"stats":{"minecraft:custom":{"minecraft:jump":50,"minecraft:time_since_rest":2747,"minecraft:play_time_without_seven_curses":4457,"minecraft:damage_taken":10,"minecraft:crouch_one_cm":17,"minecraft:leave_game":2,"minecraft:play_time":4487,"minecraft:sprint_one_cm":2018,"minecraft:time_since_death":2716,"minecraft:walk_one_cm":21286,"minecraft:deaths":1,"minecraft:sneak_time":19,"minecraft:total_world_time":6724,"minecraft:fall_one_cm":894,"minecraft:fly_one_cm":8028},"minecraft:used":{"minecraft:map":4}},"DataVersion":2975}